e5lora/__init__.py
e5lora/board.py
e5lora-0.6.0.dist-info/LICENSE
e5lora-0.6.0.dist-info/METADATA
e5lora-0.6.0.dist-info/WHEEL
e5lora-0.6.0.dist-info/top_level.txt
e5lora-0.6.0.dist-info/RECORD
