Metadata-Version: 2.1
Name: e5lora
Version: 0.6.0
Summary: Facilitates use of a SEEED Studio E5 LoRaWAN module.
Author-email: Alan Mitchell <alan@analysisnorth.com>
License: MIT License        
Project-URL: Homepage, https://github.com/alanmitchell/e5lora
Keywords: LoRa,E5,SEEED
Classifier: License :: OSI Approved :: MIT License
Classifier: Programming Language :: Python
Classifier: Programming Language :: Python :: 3
Requires-Python: >=3.6
License-File: LICENSE
Requires-Dist: pyserial (>=3.5)
